komlogd/__init__.py
komlogd/main.py
komlogd/version.py
komlogd/api/__init__.py
komlogd/api/crypto.py
komlogd/api/exceptions.py
komlogd/api/logging.py
komlogd/api/session.py
komlogd/api/transfer_methods.py
komlogd/api/common/__init__.py
komlogd/api/common/crypto.py
komlogd/api/common/exceptions.py
komlogd/api/common/logging.py
komlogd/api/common/timeuuid.py
komlogd/api/common/tests/__init__.py
komlogd/api/common/tests/test_crypto.py
komlogd/api/common/tests/test_timeuuid.py
komlogd/api/model/__init__.py
komlogd/api/model/metrics.py
komlogd/api/model/queues.py
komlogd/api/model/schedules.py
komlogd/api/model/session.py
komlogd/api/model/store.py
komlogd/api/model/test.py
komlogd/api/model/transactions.py
komlogd/api/model/transfer_methods.py
komlogd/api/model/tests/__init__.py
komlogd/api/model/tests/test_metrics.py
komlogd/api/model/tests/test_schedules.py
komlogd/api/model/tests/test_session.py
komlogd/api/model/tests/test_store.py
komlogd/api/model/tests/test_transactions.py
komlogd/api/model/tests/test_transfer_methods.py
komlogd/api/protocol/__init__.py
komlogd/api/protocol/codes.py
komlogd/api/protocol/messages.py
komlogd/api/protocol/validation.py
komlogd/api/protocol/processing/__init__.py
komlogd/api/protocol/processing/message.py
komlogd/api/protocol/processing/procedure.py
komlogd/api/protocol/processing/tests/__init__.py
komlogd/api/protocol/processing/tests/test_message.py
komlogd/api/protocol/processing/tests/test_procedure.py
komlogd/api/protocol/tests/__init__.py
komlogd/api/protocol/tests/test_messages.py
komlogd/api/protocol/tests/test_validation.py
komlogd/api/tests/__init__.py
komlogd/api/tests/test_crypto.py
komlogd/api/tests/test_session.py
komlogd/api/tests/test_transfer_methods.py
komlogd/base/__init__.py
komlogd/base/config.py
komlogd/base/crypto.py
komlogd/base/exceptions.py
komlogd/base/logging.py
komlogd/base/packages.py
komlogd/base/session.py
komlogd/base/settings/__init__.py
komlogd-0.12.0.dist-info/DESCRIPTION.rst
komlogd-0.12.0.dist-info/METADATA
komlogd-0.12.0.dist-info/RECORD
komlogd-0.12.0.dist-info/WHEEL
komlogd-0.12.0.dist-info/entry_points.txt
komlogd-0.12.0.dist-info/metadata.json
komlogd-0.12.0.dist-info/top_level.txt
