Metadata-Version: 2.0
Name: komlogd
Version: 0.12.0
Summary: Komlog agent
Home-page: https://github.com/komlog-io/komlogd
Author: komlog Team
Author-email: hello@komlog.io
License: Apache Software License
Platform: UNKNOWN
Classifier: Development Status :: 4 - Beta
Classifier: Intended Audience :: Developers
Classifier: Intended Audience :: Information Technology
Classifier: Intended Audience :: System Administrators
Classifier: License :: OSI Approved :: Apache Software License
Classifier: Programming Language :: Python :: 3 :: Only
Classifier: Programming Language :: Python :: 3.5
Classifier: Programming Language :: Python :: 3.6
Classifier: Topic :: Software Development :: Build Tools
Classifier: Topic :: System :: Monitoring
Classifier: Topic :: System :: Systems Administration
Classifier: Topic :: Utilities
Requires-Dist: aiohttp (>=2.0)
Requires-Dist: cryptography (>=2.0)
Requires-Dist: pandas (>=0.18.1)
Requires-Dist: pyyaml
Requires-Dist: setuptools
